README.md
setup.py
FDMTools/Helpper.py
FDMTools/LoadConditions.py
FDMTools/Lockin.py
FDMTools/ReadRecordingFiles.py
FDMTools/__init__.py
FDMTools.egg-info/PKG-INFO
FDMTools.egg-info/SOURCES.txt
FDMTools.egg-info/dependency_links.txt
FDMTools.egg-info/entry_points.txt
FDMTools.egg-info/top_level.txt